map2model.cpython-312-darwin.so
map2model-1.2.1.dist-info/RECORD
map2model-1.2.1.dist-info/WHEEL
map2model-1.2.1.dist-info/METADATA
map2model-1.2.1.dist-info/licenses/LICENSE
